actag-1.0.1.dist-info/METADATA
actag-1.0.1.dist-info/WHEEL
actag-1.0.1.dist-info/license_files/LICENSE.md
actag/__init__.py
actag/tag_parameters.py
actag/generated_families/AcTag24h4.java
actag/generated_families/AcTag24h6.java
actag/generated_families/AcTag24h8.java
actag/generated_families/AcTag24h10.java
actag/median_filter.py
actag/sonar_parameters.py
actag/contour_identification.py
actag/adaptive_threshold.py
actag/tag_decoding.py
actag/actag_src.py
actag/quad_fitting.py
actag/rust_impl.cpython-310-x86_64-linux-gnu.so
actag-1.0.1.dist-info/RECORD
