Metadata-Version: 2.1
Name: actag
Version: 1.0.1
Classifier: Programming Language :: Rust
Classifier: Programming Language :: Python :: Implementation :: CPython
Classifier: Programming Language :: Python :: Implementation :: PyPy
Classifier: Programming Language :: Python :: 3.10
Classifier: Programming Language :: Python :: 3.11
Requires-Dist: opencv-python
Requires-Dist: matplotlib
Requires-Dist: numpy
Requires-Dist: maturin
Requires-Dist: patchelf
License-File: LICENSE.md
Summary: AcTag: Opti-Acoustic Fiducial Markers for Underwater Localization and Mapping
License: BSD-2-Clause
Requires-Python: >=3.10
